{
  "weather": [
    { "name": "Tirana", "country": "Albania", "weather": { "temperature": 16, "wind": 8 }, "id": "tirana-albania" },
    { "name": "Andorra la Vella", "country": "Andorra", "weather": { "temperature": 12, "wind": 10 }, "id": "andorra-la-vella-andorra" },
    { "name": "Vienna", "country": "Austria", "weather": { "temperature": 11, "wind": 12 }, "id": "vienna-austria" },
    { "name": "Minsk", "country": "Belarus", "weather": { "temperature": 5, "wind": 15 }, "id": "minsk-belarus" },
    { "name": "Brussels", "country": "Belgium", "weather": { "temperature": 10, "wind": 14 }, "id": "brussels-belgium" },
    { "name": "Sarajevo", "country": "Bosnia and Herzegovina", "weather": { "temperature": 10, "wind": 7 }, "id": "sarajevo-bosnia-and-herzegovina" },
    { "name": "Sofia", "country": "Bulgaria", "weather": { "temperature": 12, "wind": 9 }, "id": "sofia-bulgaria" },
    { "name": "Zagreb", "country": "Croatia", "weather": { "temperature": 13, "wind": 6 }, "id": "zagreb-croatia" },
    { "name": "Nicosia", "country": "Cyprus", "weather": { "temperature": 19, "wind": 11 }, "id": "nicosia-cyprus" },
    { "name": "Prague", "country": "Czechia", "weather": { "temperature": 9, "wind": 13 }, "id": "prague-czechia" },
    { "name": "Copenhagen", "country": "Denmark", "weather": { "temperature": 6, "wind": 18 }, "id": "copenhagen-denmark" },
    { "name": "Tallinn", "country": "Estonia", "weather": { "temperature": 2, "wind": 20 }, "id": "tallinn-estonia" },
    { "name": "Helsinki", "country": "Finland", "weather": { "temperature": 1, "wind": 17 }, "id": "helsinki-finland" },
    { "name": "Paris", "country": "France", "weather": { "temperature": 13, "wind": 12 }, "id": "paris-france" },
    { "name": "Berlin", "country": "Germany", "weather": { "temperature": 8, "wind": 14 }, "id": "berlin-germany" },
    { "name": "Athens", "country": "Greece", "weather": { "temperature": 17, "wind": 15 }, "id": "athens-greece" },
    { "name": "Budapest", "country": "Hungary", "weather": { "temperature": 12, "wind": 10 }, "id": "budapest-hungary" },
    { "name": "Reykjavik", "country": "Iceland", "weather": { "temperature": 2, "wind": 25 }, "id": "reykjavik-iceland" },
    { "name": "Dublin", "country": "Ireland", "weather": { "temperature": 9, "wind": 22 }, "id": "dublin-ireland" },
    { "name": "Rome", "country": "Italy", "weather": { "temperature": 16, "wind": 9 }, "id": "rome-italy" },
    { "name": "Riga", "country": "Latvia", "weather": { "temperature": 3, "wind": 16 }, "id": "riga-latvia" },
    { "name": "Vaduz", "country": "Liechtenstein", "weather": { "temperature": 10, "wind": 5 }, "id": "vaduz-liechtenstein" },
    { "name": "Vilnius", "country": "Lithuania", "weather": { "temperature": 4, "wind": 14 }, "id": "vilnius-lithuania" },
    { "name": "Luxembourg", "country": "Luxembourg", "weather": { "temperature": 9, "wind": 11 }, "id": "luxembourg-luxembourg" },
    { "name": "Valletta", "country": "Malta", "weather": { "temperature": 18, "wind": 14 }, "id": "valletta-malta" },
    { "name": "Chisinau", "country": "Moldova", "weather": { "temperature": 9, "wind": 12 }, "id": "chisinau-moldova" },
    { "name": "Monaco", "country": "Monaco", "weather": { "temperature": 15, "wind": 10 }, "id": "monaco-monaco" },
    { "name": "Podgorica", "country": "Montenegro", "weather": { "temperature": 15, "wind": 7 }, "id": "podgorica-montenegro" },
    { "name": "Amsterdam", "country": "Netherlands", "weather": { "temperature": 9, "wind": 18 }, "id": "amsterdam-netherlands" },
    { "name": "Skopje", "country": "North Macedonia", "weather": { "temperature": 14, "wind": 6 }, "id": "skopje-north-macedonia" },
    { "name": "Oslo", "country": "Norway", "weather": { "temperature": 4, "wind": 12 }, "id": "oslo-norway" },
    { "name": "Warsaw", "country": "Poland", "weather": { "temperature": 8, "wind": 13 }, "id": "warsaw-poland" },
    { "name": "Lisbon", "country": "Portugal", "weather": { "temperature": 18, "wind": 12 }, "id": "lisbon-portugal" },
    { "name": "Bucharest", "country": "Romania", "weather": { "temperature": 12, "wind": 11 }, "id": "bucharest-romania" },
    { "name": "Moscow", "country": "Russia", "weather": { "temperature": 2, "wind": 14 }, "id": "moscow-russia" },
    { "name": "San Marino", "country": "San Marino", "weather": { "temperature": 13, "wind": 10 }, "id": "san-marino-san-marino" },
    { "name": "Belgrade", "country": "Serbia", "weather": { "temperature": 13, "wind": 11 }, "id": "belgrade-serbia" },
    { "name": "Bratislava", "country": "Slovakia", "weather": { "temperature": 11, "wind": 14 }, "id": "bratislava-slovakia" },
    { "name": "Ljubljana", "country": "Slovenia", "weather": { "temperature": 12, "wind": 8 }, "id": "ljubljana-slovenia" },
    { "name": "Madrid", "country": "Spain", "weather": { "temperature": 17, "wind": 10 }, "id": "madrid-spain" },
    { "name": "Stockholm", "country": "Sweden", "weather": { "temperature": 4, "wind": 15 }, "id": "stockholm-sweden" },
    { "name": "Bern", "country": "Switzerland", "weather": { "temperature": 10, "wind": 7 }, "id": "bern-switzerland" },
    { "name": "Kyiv", "country": "Ukraine", "weather": { "temperature": 7, "wind": 13 }, "id": "kyiv-ukraine" },
    { "name": "London", "country": "United Kingdom", "weather": { "temperature": 11, "wind": 16 }, "id": "london-united-kingdom" },
    { "name": "Vatican City", "country": "Vatican City", "weather": { "temperature": 16, "wind": 5 }, "id": "vatican-city-vatican-city" }
  ],
  "$schema": "./node_modules/json-server/schema.json"
}
